{"lastUsed":1667351948881,"path":"C:\/Users\/cuerpos\/OneDrive\/Desktop\/TPS_Laboratorio_1\/tps_laboratorio_1","projectCount":2,"recentFiles":[{"path":"\/tp3_windows","parentWorkspace":"C:\/Users\/cuerpos\/OneDrive\/Desktop\/TPS_Laboratorio_1\/tps_laboratorio_1","name":"Jugador.c","lastModified":1667349885792,"locationURI":"file:\/C:\/Users\/cuerpos\/OneDrive\/Desktop\/TPS_Laboratorio_1\/tps_laboratorio_1\/tp3_windows\/Jugador.c"},{"path":"\/tp3_windows","parentWorkspace":"C:\/Users\/cuerpos\/OneDrive\/Desktop\/TPS_Laboratorio_1\/tps_laboratorio_1","name":"Jugador.h","lastModified":1667349885777,"locationURI":"file:\/C:\/Users\/cuerpos\/OneDrive\/Desktop\/TPS_Laboratorio_1\/tps_laboratorio_1\/tp3_windows\/Jugador.h"},{"path":"\/tp3_windows","parentWorkspace":"C:\/Users\/cuerpos\/OneDrive\/Desktop\/TPS_Laboratorio_1\/tps_laboratorio_1","name":"Controller.h","lastModified":1667337666940,"locationURI":"file:\/C:\/Users\/cuerpos\/OneDrive\/Desktop\/TPS_Laboratorio_1\/tps_laboratorio_1\/tp3_windows\/Controller.h"},{"path":"\/tp3_windows","parentWorkspace":"C:\/Users\/cuerpos\/OneDrive\/Desktop\/TPS_Laboratorio_1\/tps_laboratorio_1","name":"Seleccion.c","lastModified":1667350054153,"locationURI":"file:\/C:\/Users\/cuerpos\/OneDrive\/Desktop\/TPS_Laboratorio_1\/tps_laboratorio_1\/tp3_windows\/Seleccion.c"},{"path":"\/tp3_windows","parentWorkspace":"C:\/Users\/cuerpos\/OneDrive\/Desktop\/TPS_Laboratorio_1\/tps_laboratorio_1","name":"Seleccion.h","lastModified":1667349885768,"locationURI":"file:\/C:\/Users\/cuerpos\/OneDrive\/Desktop\/TPS_Laboratorio_1\/tps_laboratorio_1\/tp3_windows\/Seleccion.h"},{"path":"\/modelo-tp-3\/src","parentWorkspace":"C:\/Users\/cuerpos\/OneDrive\/Desktop\/TPS_Laboratorio_1\/tps_laboratorio_1","name":"parser.c","lastModified":1667347550574,"locationURI":"file:\/C:\/Users\/cuerpos\/OneDrive\/Desktop\/PRIMERPARCIAL-LABO1\/Emmanuel_Martin_parciales_1-E_Laboratorio-1\/modelo-tp-3\/src\/parser.c"},{"path":"\/tp3_windows","parentWorkspace":"C:\/Users\/cuerpos\/OneDrive\/Desktop\/TPS_Laboratorio_1\/tps_laboratorio_1","name":"parser.c","lastModified":1667351948881,"locationURI":"file:\/C:\/Users\/cuerpos\/OneDrive\/Desktop\/TPS_Laboratorio_1\/tps_laboratorio_1\/tp3_windows\/parser.c"}]}